<?xml version="1.0" encoding="utf-8" ?><dwsync><file name="lang.cs.js" server="tinkeringdesigns.com//www/" local="3640629903" remote="3611199600" Dst="-1" /><file name="lang.de.js" server="tinkeringdesigns.com//www/" local="3640629903" remote="3611199600" Dst="-1" /><file name="lang.en.js" server="tinkeringdesigns.com//www/" local="3640629904" remote="3611199600" Dst="-1" /><file name="lang.es.js" server="tinkeringdesigns.com//www/" local="3640629904" remote="3611199600" Dst="-1" /><file name="lang.fr.js" server="tinkeringdesigns.com//www/" local="3640629904" remote="3611199600" Dst="-1" /><file name="lang.he.js" server="tinkeringdesigns.com//www/" local="3640629904" remote="3611199600" Dst="-1" /><file name="lang.hr.js" server="tinkeringdesigns.com//www/" local="3640629904" remote="3611199600" Dst="-1" /><file name="lang.it.js" server="tinkeringdesigns.com//www/" local="3640629904" remote="3611199600" Dst="-1" /><file name="lang.ja.js" server="tinkeringdesigns.com//www/" local="3640629904" remote="3611199600" Dst="-1" /><file name="lang.nl.js" server="tinkeringdesigns.com//www/" local="3640629904" remote="3611199600" Dst="-1" /><file name="lang.pl.js" server="tinkeringdesigns.com//www/" local="3640629904" remote="3611199600" Dst="-1" /><file name="lang.pt_br.js" server="tinkeringdesigns.com//www/" local="3640629904" remote="3611199600" Dst="-1" /><file name="lang.ru.js" server="tinkeringdesigns.com//www/" local="3640629904" remote="3611199600" Dst="-1" /><file name="lang.se.js" server="tinkeringdesigns.com//www/" local="3640629904" remote="3611199600" Dst="-1" /><file name="lang.zh-cn.js" server="tinkeringdesigns.com//www/" local="3640629905" remote="3611199600" Dst="-1" /><file name="lang.sl.js" server="tinkeringdesigns.com//www/" local="3640629905" remote="3611199600" Dst="-1" /></dwsync>