<?xml version="1.0" encoding="utf-8" ?><dwsync><file name="extension.class.php" server="marielamagallon.com/public_html/" local="3628027772" remote="3627700500" Dst="-1" /><file name="external-sources.class.php" server="marielamagallon.com/public_html/" local="3628027773" remote="3627700500" Dst="-1" /><file name="globals.class.php" server="marielamagallon.com/public_html/" local="3628027782" remote="3627700500" Dst="-1" /><file name="googlefonts.php" server="marielamagallon.com/public_html/" local="3628027784" remote="3627700500" Dst="-1" /><file name="index.php" server="marielamagallon.com/public_html/" local="3628027797" remote="3627700500" Dst="-1" /><file name="object-library.class.php" server="marielamagallon.com/public_html/" local="3628027799" remote="3627700500" Dst="-1" /><file name="navigation.class.php" server="marielamagallon.com/public_html/" local="3628027804" remote="3627700500" Dst="-1" /><file name="page-template.class.php" server="marielamagallon.com/public_html/" local="3628027804" remote="3627700500" Dst="-1" /><file name="operations.class.php" server="marielamagallon.com/public_html/" local="3628027805" remote="3627700500" Dst="-1" /><file name="slide.class.php" server="marielamagallon.com/public_html/" local="3628027807" remote="3627700500" Dst="-1" /><file name="slider.class.php" server="marielamagallon.com/public_html/" local="3628027807" remote="3627700500" Dst="-1" /><file name="output.class.php" server="marielamagallon.com/public_html/" local="3628027807" remote="3627700500" Dst="-1" /><file name="template.class.php" server="marielamagallon.com/public_html/" local="3628027807" remote="3627700500" Dst="-1" /><file name="tinybox.class.php" server="marielamagallon.com/public_html/" local="3628027808" remote="3627700500" Dst="-1" /><file name="widget.class.php" server="marielamagallon.com/public_html/" local="3628027808" remote="3627700500" Dst="-1" /></dwsync>