<?xml version="1.0" encoding="utf-8" ?><dwsync><file name="jquery.effects.bounce.js" server="haliburton.online/www/" local="3619625279" remote="3611183040" Dst="-1" /><file name="jquery.effects.blind.js" server="haliburton.online/www/" local="3619625279" remote="3611183040" Dst="-1" /><file name="jquery.effects.drop.js" server="haliburton.online/www/" local="3619625280" remote="3611183040" Dst="-1" /><file name="jquery.effects.clip.js" server="haliburton.online/www/" local="3619625280" remote="3611183040" Dst="-1" /><file name="jquery.effects.core.js" server="haliburton.online/www/" local="3619625280" remote="3611183040" Dst="-1" /><file name="jquery.effects.explode.js" server="haliburton.online/www/" local="3619625280" remote="3611183040" Dst="-1" /><file name="jquery.effects.fold.js" server="haliburton.online/www/" local="3619625280" remote="3611183040" Dst="-1" /><file name="jquery.effects.highlight.js" server="haliburton.online/www/" local="3619625280" remote="3611183040" Dst="-1" /><file name="jquery.effects.shake.js" server="haliburton.online/www/" local="3619625280" remote="3611183040" Dst="-1" /><file name="jquery.effects.pulsate.js" server="haliburton.online/www/" local="3619625280" remote="3611183040" Dst="-1" /><file name="jquery.effects.scale.js" server="haliburton.online/www/" local="3619625280" remote="3611183040" Dst="-1" /><file name="jquery.effects.slide.js" server="haliburton.online/www/" local="3619625280" remote="3611183040" Dst="-1" /><file name="jquery.effects.transfer.js" server="haliburton.online/www/" local="3619625280" remote="3611183040" Dst="-1" /><file name="jquery.ui.accordion.css" server="haliburton.online/www/" local="3619625280" remote="3611183040" Dst="-1" /><file name="jquery.ui.all.css" server="haliburton.online/www/" local="3619625280" remote="3611183040" Dst="-1" /><file name="jquery.ui.accordion.js" server="haliburton.online/www/" local="3619625280" remote="3611183040" Dst="-1" /><file name="jquery.ui.autocomplete.css" server="haliburton.online/www/" local="3619625281" remote="3611183040" Dst="-1" /><file name="jquery.ui.base.css" server="haliburton.online/www/" local="3619625281" remote="3611183040" Dst="-1" /><file name="jquery.ui.autocomplete.js" server="haliburton.online/www/" local="3619625281" remote="3611183040" Dst="-1" /><file name="jquery.ui.button.css" server="haliburton.online/www/" local="3619625281" remote="3611183040" Dst="-1" /><file name="jquery.ui.button.js" server="haliburton.online/www/" local="3619625281" remote="3611183040" Dst="-1" /><file name="jquery.ui.core.css" server="haliburton.online/www/" local="3619625281" remote="3611183040" Dst="-1" /><file name="jquery.ui.core.js" server="haliburton.online/www/" local="3619625281" remote="3611183040" Dst="-1" /><file name="jquery.ui.datepicker.css" server="haliburton.online/www/" local="3619625281" remote="3611183040" Dst="-1" /><file name="jquery.ui.datepicker.js" server="haliburton.online/www/" local="3619625281" remote="3611183040" Dst="-1" /><file name="jquery.ui.dialog.css" server="haliburton.online/www/" local="3619625281" remote="3611183040" Dst="-1" /><file name="jquery.ui.dialog.js" server="haliburton.online/www/" local="3619625281" remote="3611183040" Dst="-1" /><file name="jquery.ui.droppable.js" server="haliburton.online/www/" local="3619625281" remote="3611183040" Dst="-1" /><file name="jquery.ui.draggable.js" server="haliburton.online/www/" local="3619625282" remote="3611183040" Dst="-1" /><file name="jquery.ui.mouse.js" server="haliburton.online/www/" local="3619625282" remote="3611183040" Dst="-1" /><file name="jquery.ui.position.js" server="haliburton.online/www/" local="3619625282" remote="3611183040" Dst="-1" /><file name="jquery.ui.progressbar.css" server="haliburton.online/www/" local="3619625282" remote="3611183040" Dst="-1" /><file name="jquery.ui.progressbar.js" server="haliburton.online/www/" local="3619625282" remote="3611183040" Dst="-1" /><file name="jquery.ui.resizable.css" server="haliburton.online/www/" local="3619625282" remote="3611183040" Dst="-1" /><file name="jquery.ui.resizable.js" server="haliburton.online/www/" local="3619625282" remote="3611183040" Dst="-1" /><file name="jquery.ui.slider.css" server="haliburton.online/www/" local="3619625282" remote="3611183040" Dst="-1" /><file name="jquery.ui.selectable.js" server="haliburton.online/www/" local="3619625282" remote="3611183040" Dst="-1" /><file name="jquery.ui.slider.js" server="haliburton.online/www/" local="3619625282" remote="3611183040" Dst="-1" /><file name="jquery.ui.tabs.css" server="haliburton.online/www/" local="3619625282" remote="3611183040" Dst="-1" /><file name="jquery.ui.sortable.js" server="haliburton.online/www/" local="3619625282" remote="3611183040" Dst="-1" /><file name="jquery.ui.widget.js" server="haliburton.online/www/" local="3619625282" remote="3611183040" Dst="-1" /><file name="jquery.ui.tabs.js" server="haliburton.online/www/" local="3619625282" remote="3611183040" Dst="-1" /><file name="jquery.ui.theme.css" server="haliburton.online/www/" local="3619625282" remote="3611183040" Dst="-1" /></dwsync>